labeled_lda/__init__.py
labeled_lda/llda.py
labeled_lda/llda_core.py
labeled_lda/preprocess.py
labeled_lda-0.0.1a0.dist-info/LICENSE
labeled_lda-0.0.1a0.dist-info/METADATA
labeled_lda-0.0.1a0.dist-info/WHEEL
labeled_lda-0.0.1a0.dist-info/top_level.txt
labeled_lda-0.0.1a0.dist-info/RECORD
