Metadata-Version: 2.1
Name: labeled-lda
Version: 0.0.1a0
Summary: A toolkit to perform labeled LDA models
Author-email: Donghua Chen <douglaschan@126.com>
License: MIT License
Project-URL: Homepage, https://github.com/dhchenx/labeled-lda
Project-URL: Bug Reports, https://github.com/dhchenx/labeled-lda/issues
Project-URL: Source, https://github.com/dhchenx/labeled-lda/
Keywords: Labeled LDA
Classifier: Development Status :: 5 - Production/Stable
Classifier: Intended Audience :: Developers
Classifier: Topic :: Software Development :: Build Tools
Classifier: License :: OSI Approved :: MIT License
Classifier: Programming Language :: Python :: 3
Classifier: Programming Language :: Python :: 3.7
Classifier: Programming Language :: Python :: 3.8
Classifier: Programming Language :: Python :: 3.9
Classifier: Programming Language :: Python :: 3.10
Classifier: Programming Language :: Python :: 3.11
Classifier: Programming Language :: Python :: 3 :: Only
Requires-Python: >=3.7
License-File: LICENSE
Requires-Dist: jieba
Requires-Dist: numpy
Provides-Extra: dev
Requires-Dist: check-manifest ; extra == 'dev'
Provides-Extra: test
Requires-Dist: coverage ; extra == 'test'
